personal_assistant_group_03/__init__.py
personal_assistant_group_03/address_book.py
personal_assistant_group_03/main.py
personal_assistant_group_03/notebook.py
personal_assistant_group_03/sorting.py
personal_cli_assistant-0.0.5.dist-info/METADATA
personal_cli_assistant-0.0.5.dist-info/WHEEL
personal_cli_assistant-0.0.5.dist-info/entry_points.txt
personal_cli_assistant-0.0.5.dist-info/top_level.txt
personal_cli_assistant-0.0.5.dist-info/RECORD
